get_tax_info/__init__.py
get_tax_info/cli.py
get_tax_info/get_busco.py
get_tax_info/get_tax_info.py
get_tax_info/tax_id.py
get_tax_info/utils.py
get_tax_info-0.2.1.dist-info/METADATA
get_tax_info-0.2.1.dist-info/WHEEL
get_tax_info-0.2.1.dist-info/entry_points.txt
get_tax_info-0.2.1.dist-info/licenses/LICENSE
get_tax_info-0.2.1.dist-info/RECORD
