Metadata-Version: 2.4
Name: get-tax-info
Version: 0.2.1
Summary: Convert NCBI TaxIDs to scientific species names and vice-versa
Project-URL: Homepage, https://github.com/MrTomRod/get-tax-info
Author-email: Thomas Roder <roder.thomas@gmail.com>
License: MIT
License-File: LICENSE
Classifier: License :: OSI Approved :: MIT License
Classifier: Programming Language :: Python :: 3
Classifier: Programming Language :: Python :: 3.9
Classifier: Programming Language :: Python :: 3.10
Classifier: Programming Language :: Python :: 3.11
Classifier: Programming Language :: Python :: 3.12
Classifier: Programming Language :: Python :: 3.13
Classifier: Programming Language :: Python :: 3.14
Requires-Python: >=3.9
Requires-Dist: fire
Requires-Dist: pandas
Requires-Dist: platformdirs
